kafkacfg/__init__.py
kafkacfg/broker.py
kafkacfg/cli.py
kafkacfg/config.py
kafkacfg/data/kafka/0.10.0.json
kafkacfg/data/kafka/0.10.1.json
kafkacfg/data/kafka/0.10.2.json
kafkacfg/data/kafka/0.11.0.json
kafkacfg/data/kafka/0.7.json
kafkacfg/data/kafka/0.8.1.json
kafkacfg/data/kafka/0.8.2.json
kafkacfg/data/kafka/0.8.json
kafkacfg/data/kafka/0.9.0.json
kafkacfg/data/kafka/1.0.json
kafkacfg/data/kafka/1.1.json
kafkacfg/data/kafka/2.0.json
kafkacfg/data/kafka/2.1.json
kafkacfg/data/kafka/2.2.json
kafkacfg/data/kafka/2.3.json
kafkacfg/data/kafka/2.4.json
kafkacfg/data/kafka/2.5.json
kafkacfg/data/kafka/2.6.json
kafkacfg/data/kafka/2.7.json
kafkacfg/data/kafka/2.8.json
kafkacfg/data/kafka/3.0.json
kafkacfg/data/kafka/3.1.json
kafkacfg/data/kafka/3.2.json
kafkacfg/data/kafka/3.3.json
kafkacfg/data/kafka/3.4.json
kafkacfg/data/kafka/3.5.json
kafkacfg/data/kafka/3.6.json
kafkacfg/data/kafka/3.7.json
kafkacfg/data/kafka/3.8.json
kafkacfg/data/kafka/3.9.json
kafkacfg/data/kafka/4.0.json
kafkacfg/data/librdkafka/0.8.0.json
kafkacfg/data/librdkafka/0.8.1.json
kafkacfg/data/librdkafka/0.8.2.json
kafkacfg/data/librdkafka/0.8.3.json
kafkacfg/data/librdkafka/0.8.4.json
kafkacfg/data/librdkafka/0.8.5.json
kafkacfg/data/librdkafka/0.8.6.json
kafkacfg/data/librdkafka/0.9.0.100.json
kafkacfg/data/librdkafka/0.9.0.101.json
kafkacfg/data/librdkafka/0.9.0.99.json
kafkacfg/data/librdkafka/0.9.0.json
kafkacfg/data/librdkafka/0.9.1.json
kafkacfg/data/librdkafka/0.9.2.json
kafkacfg/data/librdkafka/0.9.3.json
kafkacfg/data/librdkafka/0.9.4.json
kafkacfg/data/librdkafka/0.9.5.json
kafkacfg/data/librdkafka/1.0.0.json
kafkacfg/data/librdkafka/1.0.1.json
kafkacfg/data/librdkafka/1.1.0.json
kafkacfg/data/librdkafka/1.2.0.json
kafkacfg/data/librdkafka/1.2.1.json
kafkacfg/data/librdkafka/1.2.2.json
kafkacfg/data/librdkafka/1.3.0.json
kafkacfg/data/librdkafka/1.4.0.json
kafkacfg/data/librdkafka/1.4.2.json
kafkacfg/data/librdkafka/1.4.4.json
kafkacfg/data/librdkafka/1.5.0.json
kafkacfg-0.8.0.dist-info/METADATA
kafkacfg-0.8.0.dist-info/WHEEL
kafkacfg-0.8.0.dist-info/entry_points.txt
kafkacfg-0.8.0.dist-info/licenses/LICENSE
kafkacfg-0.8.0.dist-info/RECORD
