Metadata-Version: 2.4
Name: kafkacfg
Version: 0.8.0
Summary: Kafka configuration inspector
License: MIT
License-File: LICENSE
Author: Balthazar Rouberol
Author-email: br@imap.cc
Requires-Python: >=3.9,<4.0
Classifier: License :: OSI Approved :: MIT License
Classifier: Programming Language :: Python :: 3
Classifier: Programming Language :: Python :: 3.9
Classifier: Programming Language :: Python :: 3.10
Classifier: Programming Language :: Python :: 3.11
Classifier: Programming Language :: Python :: 3.12
Classifier: Programming Language :: Python :: 3.13
Classifier: Programming Language :: Python :: 3.14
Requires-Dist: click (>=8.1.7,<9.0.0)
